<?xml version="1.0" encoding="UTF-8"?>
<objects serializationModel="Studio.02.02.00">
	<object class="EncodingSetting" id="{4647bdfc-f012-40a4-907a-79b7757be791}">
		<property name="encodingFormat">
			<value>3</value>
		</property>
		<property name="quality">
			<value>20</value>
		</property>
		<property name="sampleRate">
			<value>30000</value>
		</property>
		<relationship name="platform">
			<destination>{56ca4293-97ac-4cfc-b7a5-33a140be17b6}</destination>
		</relationship>
		<relationship name="encodable">
			<destination>{85eedcb6-0f8c-45d1-b490-281f5beb1738}</destination>
		</relationship>
	</object>
</objects>
