<?xml version="1.0" encoding="UTF-8"?>
<objects serializationModel="Studio.02.02.00">
	<object class="EncodingSetting" id="{6d54dc4a-b31a-4c36-a35f-c69bd34e3aa1}">
		<property name="encodingFormat">
			<value>3</value>
		</property>
		<property name="quality">
			<value>20</value>
		</property>
		<property name="sampleRate">
			<value>30000</value>
		</property>
		<relationship name="platform">
			<destination>{56ca4293-97ac-4cfc-b7a5-33a140be17b6}</destination>
		</relationship>
		<relationship name="encodable">
			<destination>{65b390c3-ca16-4dd7-9c83-710f6f467854}</destination>
		</relationship>
	</object>
</objects>
